sinapsis_data_analysis/src/sinapsis_data_analysis/__init__.py
sinapsis_data_analysis/src/sinapsis_data_analysis/helpers/__init__.py
sinapsis_data_analysis/src/sinapsis_data_analysis/helpers/excluded_models.py
sinapsis_data_analysis/src/sinapsis_data_analysis/helpers/model_metrics.py
sinapsis_data_analysis/src/sinapsis_data_analysis/helpers/tags.py
sinapsis_data_analysis/src/sinapsis_data_analysis/templates/__init__.py
sinapsis_data_analysis/src/sinapsis_data_analysis/templates/ml_base_inference.py
sinapsis_data_analysis/src/sinapsis_data_analysis/templates/ml_base_training.py
sinapsis_data_analysis/src/sinapsis_data_analysis/templates/sklearn_inference.py
sinapsis_data_analysis/src/sinapsis_data_analysis/templates/sklearn_manifold.py
sinapsis_data_analysis/src/sinapsis_data_analysis/templates/sklearn_train.py
sinapsis_data_analysis/src/sinapsis_data_analysis/templates/xgboost_inference.py
sinapsis_data_analysis/src/sinapsis_data_analysis/templates/xgboost_train.py
sinapsis_data_readers/src/test_gradio_client.py
sinapsis_data_readers/src/sinapsis_data_readers/__init__.py
sinapsis_data_readers/src/sinapsis_data_readers/helpers/__init__.py
sinapsis_data_readers/src/sinapsis_data_readers/helpers/coco_dataclasses.py
sinapsis_data_readers/src/sinapsis_data_readers/helpers/csv_reader.py
sinapsis_data_readers/src/sinapsis_data_readers/helpers/file_path_helpers.py
sinapsis_data_readers/src/sinapsis_data_readers/helpers/sklearn_dataset_subset.py
sinapsis_data_readers/src/sinapsis_data_readers/helpers/sktime_datasets_subset.py
sinapsis_data_readers/src/sinapsis_data_readers/helpers/tags.py
sinapsis_data_readers/src/sinapsis_data_readers/helpers/text_input_helpers.py
sinapsis_data_readers/src/sinapsis_data_readers/templates/__init__.py
sinapsis_data_readers/src/sinapsis_data_readers/templates/base_file_data_loader.py
sinapsis_data_readers/src/sinapsis_data_readers/templates/audio_readers/__init__.py
sinapsis_data_tools-0.2.24.dist-info/licenses/LICENSE
sinapsis_data_tools-0.2.24.dist-info/METADATA
sinapsis_data_tools-0.2.24.dist-info/WHEEL
sinapsis_data_tools-0.2.24.dist-info/top_level.txt
sinapsis_data_tools-0.2.24.dist-info/RECORD
