Metadata-Version: 2.4
Name: sinapsis-data-tools
Version: 0.2.24
Summary: Module that contains different packages to perform data-related operations through Sinapsis templates.
Author-email: SinapsisAI <dev@sinapsis.tech>
Project-URL: Homepage, https://sinapsis.tech
Project-URL: Documentation, https://docs.sinapsis.tech/docs
Project-URL: Tutorials, https://docs.sinapsis.tech/tutorials
Project-URL: Repository, https://github.com/Sinapsis-AI/sinapsis-data-tools.git
Requires-Python: >=3.10
License-File: LICENSE
Requires-Dist: sinapsis>=0.1.1
Provides-Extra: gradio-app
Requires-Dist: sinapsis[webapp]>=0.2.3; extra == "gradio-app"
Requires-Dist: pandas>=2.2.3; extra == "gradio-app"
Provides-Extra: all
Requires-Dist: sinapsis-data-analysis; extra == "all"
Requires-Dist: sinapsis-data-writers[all]; extra == "all"
Requires-Dist: sinapsis-data-readers[all]; extra == "all"
Requires-Dist: sinapsis-data-visualization[all]; extra == "all"
Requires-Dist: sinapsis-generic-data-tools[all]; extra == "all"
Dynamic: license-file
